DLMSCommunicationProfile/__init__.py
DLMSCommunicationProfile/base.py
DLMSCommunicationProfile/communication_profile.py
DLMSCommunicationProfile/limit.py
DLMSCommunicationProfile/HDLC/__init__.py
DLMSCommunicationProfile/HDLC/hdlc.py
DLMSCommunicationProfile/HDLC/negotiation.py
DLMSCommunicationProfile/MBUS/__init__.py
DLMSCommunicationProfile/MBUS/m_bus.py
DLMSCommunicationProfile/TCPUDPIP/__init__.py
DLMSCommunicationProfile/TCPUDPIP/tcp_udp_ip.py
DLMSComProf-0.0.3.dist-info/METADATA
DLMSComProf-0.0.3.dist-info/WHEEL
DLMSComProf-0.0.3.dist-info/top_level.txt
DLMSComProf-0.0.3.dist-info/RECORD
