Metadata-Version: 2.1
Name: DLMSComProf
Version: 0.0.3
Summary: dlms-spodes
Author-email: Serj Kotilevski <youserj@outlook.com>
Keywords: dlms,greenbook
Classifier: Programming Language :: Python :: 3
Classifier: License :: OSI Approved :: MIT License
Classifier: Operating System :: OS Independent
Requires-Python: >=3.12
Requires-Dist: DLMS-SPODES >=0.80.1
